PySimpleGuy/PySimpleGuy.py
PySimpleGuy/__init__.py
PySimpleGuy-1.0.0.dist-info/METADATA
PySimpleGuy-1.0.0.dist-info/WHEEL
PySimpleGuy-1.0.0.dist-info/top_level.txt
PySimpleGuy-1.0.0.dist-info/RECORD
